py5canvas/__init__.py
py5canvas/canvas.py
py5canvas/create_dummy_globals.py
py5canvas/dummy_globals.py
py5canvas/geom.py
py5canvas/gfxui.py
py5canvas/globals.py
py5canvas/notebook.py
py5canvas/run_sketch.py
py5canvas/run_sketch_bundle.py
py5canvas/run_sketch_mgl.py
py5canvas/run_sketch_pyglet.py
py5canvas/run_sketch_pyimgui.py
py5canvas/run_sketch_pyopengl.py
py5canvas/sketch.py
py5canvas/sketch_params.py
py5canvas/sketch_params_pyimgui.py
py5canvas/turtle.py
py5canvas-1.1.1.dist-info/licenses/LICENSE
py5canvas-1.1.1.dist-info/METADATA
py5canvas-1.1.1.dist-info/WHEEL
py5canvas-1.1.1.dist-info/entry_points.txt
py5canvas-1.1.1.dist-info/top_level.txt
py5canvas-1.1.1.dist-info/RECORD
