Metadata-Version: 2.4
Name: py5canvas
Version: 1.1.1
Summary: Drawings and animations with a p5.js / Processing-like API.
Author-email: Daniel Berio <drand48@gmail.com>
License: MIT
Requires-Python: >=3.9
License-File: LICENSE
Requires-Dist: numpy
Requires-Dist: pillow
Requires-Dist: PyOpenGL
Requires-Dist: moderngl
Requires-Dist: glfw
Requires-Dist: pycairo
Requires-Dist: matplotlib
Requires-Dist: rumore
Requires-Dist: easydict
Requires-Dist: xdialog
Requires-Dist: nanobind>=2.8.0
Requires-Dist: slimgui
Requires-Dist: platformdirs
Dynamic: license-file
